{
  "routes": [
    { "name": "Inicio", "path": "/" },
    { "name": "Sobre Mí", "path": "/sobre-mi" },
    { "name": "Servicios", "path": "/servicios" },
    { "name": "Paquetes", "path": "/paquetes" },
    { "name": "Testimonios", "path": "/testimonios" }
  ],

  "socialLinks": [
    {
      "name": "Facebook",
      "url": "https://facebook.com"
    },
    {
      "name": "Instagram",
      "url": "https://www.instagram.com/nutriologa.monicamtz/"
    },
    {
      "name": "Twitter",
      "url": "https://twitter.com"
    }
  ],

  "packages": [
    {
      "name": "Consulta Individual",
      "price": "$800",
      "period": "por sesión",
      "description": "Ideal para comenzar tu transformación",
      "features": [
        "Evaluación nutricional completa",
        "Plan alimenticio personalizado",
        "Recetario digital incluido",
        "Seguimiento por WhatsApp 7 días"
      ],
      "highlighted": false
    },
    {
      "name": "Paquete Mensual",
      "price": "$2,500",
      "period": "al mes",
      "description": "El más popular para resultados sostenibles",
      "features": [
        "Todo lo del paquete individual",
        "4 consultas de seguimiento",
        "Ajustes ilimitados al plan",
        "Seguimiento por WhatsApp 30 días",
        "Recetas semanales personalizadas",
        "Análisis de composición corporal"
      ],
      "highlighted": true
    },
    {
      "name": "Paquete Trimestral",
      "price": "$6,500",
      "period": "3 meses",
      "description": "Para transformaciones duraderas",
      "features": [
        "Todo lo del paquete mensual",
        "12 consultas de seguimiento",
        "Plan de mantenimiento",
        "Seguimiento por WhatsApp 90 días",
        "Asesoría en compras de supermercado",
        "Sesión de cocina saludable",
        "Descuento del 15%"
      ],
      "highlighted": false
    }
  ],

  "educacion": [
    {
      "titulo": "Licenciatura en Nutrición",
      "institucion": "Universidad Nacional Autónoma de México",
      "año": "2010-2014"
    },
    {
      "titulo": "Maestría en Nutrición Clínica",
      "institucion": "Instituto Politécnico Nacional",
      "año": "2015-2017"
    },
    {
      "titulo": "Certificación en Nutrición Deportiva",
      "institucion": "International Sports Sciences Association",
      "año": "2018"
    },
    {
      "titulo": "Diplomado en Nutrición Funcional",
      "institucion": "Instituto de Nutrición Funcional",
      "año": "2020"
    }
  ],

  "certificaciones": [
    "Certified Nutrition Specialist (CNS)",
    "Educadora en Diabetes Certificada",
    "Especialista en Nutrición Pediátrica",
    "Certificación en Mindful Eating",
    "Nutrición Oncológica Avanzada",
    "Coaching Nutricional Certificado"
  ],

  "logros": [
    { "numero": "500+", "texto": "Pacientes Transformados" },
    { "numero": "12+", "texto": "Años de Experiencia" },
    { "numero": "95%", "texto": "Tasa de Éxito" },
    { "numero": "10+", "texto": "Certificaciones" }
  ],

  "valores": [
    {
      "icon": "Heart",
      "titulo": "Empatía",
      "descripcion": "Entiendo que cada persona tiene una historia única y merece un trato personalizado y comprensivo."
    },
    {
      "icon": "Target",
      "titulo": "Resultados",
      "descripcion": "Me enfoco en estrategias probadas que generan cambios reales y sostenibles en tu salud."
    },
    {
      "icon": "Lightbulb",
      "titulo": "Innovación",
      "descripcion": "Me mantengo actualizada con las últimas investigaciones para ofrecerte los mejores tratamientos."
    },
    {
      "icon": "Star",
      "titulo": "Excelencia",
      "descripcion": "Me comprometo a brindarte el más alto nivel de servicio profesional en cada consulta."
    }
  ],

  "galeriaFotos": [
    {
      "url": "test/consultorio-nutricion-moderno.jpg",
      "alt": "Consultorio moderno y acogedor"
    },
    {
      "url": "test/nutriologa-con-paciente-consulta.jpg",
      "alt": "Consulta personalizada con paciente"
    },
    {
      "url": "test/alimentos-saludables-coloridos.jpg",
      "alt": "Alimentos saludables y nutritivos"
    },
    {
      "url": "test/plan-nutricional-personalizado.jpg",
      "alt": "Elaboración de planes personalizados"
    },
    {
      "url": "test/clase-nutricion-grupo.jpg",
      "alt": "Talleres y conferencias de nutrición"
    },
    {
      "url": "test/medicion-composicion-corporal.jpg",
      "alt": "Análisis de composición corporal"
    }
  ]
}
